protox/__init__.py
protox/constants.py
protox/encoding.py
protox/exceptions.py
protox/fields.py
protox/message.py
protox/validated_dict.py
protox/validated_list.py
protox/plugin/__init__.py
protox/plugin/common.py
protox/plugin/grpclib_code_generator.py
protox/plugin/index.py
protox/plugin/protobuf_code_generator.py
protox/well_known_types/__init__.py
protox/well_known_types/any.py
protox/well_known_types/api.py
protox/well_known_types/descriptor.py
protox/well_known_types/duration.py
protox/well_known_types/empty.py
protox/well_known_types/field_mask.py
protox/well_known_types/plugin.py
protox/well_known_types/source_context.py
protox/well_known_types/struct.py
protox/well_known_types/timestamp.py
protox/well_known_types/type.py
protox/well_known_types/wrappers.py
protox-0.1.0.dist-info/LICENSE
protox-0.1.0.dist-info/METADATA
protox-0.1.0.dist-info/WHEEL
protox-0.1.0.dist-info/entry_points.txt
protox-0.1.0.dist-info/top_level.txt
protox-0.1.0.dist-info/RECORD
