Metadata-Version: 2.1
Name: protox
Version: 0.1.0
Summary: Protobuf for humans
Home-page: http://github.com/sergey-tikhonov/protox
Author: Sergey Tikhonov
Author-email: srg.tikhonov@gmail.com
License: MIT
Platform: UNKNOWN
Classifier: Programming Language :: Python :: 3
Classifier: License :: OSI Approved :: MIT License
Classifier: Operating System :: OS Independent
Requires-Python: >=3.6
